chainsync/__init__.py
chainsync/chainsync.py
chainsync/adapters/__init__.py
chainsync/adapters/abstract/__init__.py
chainsync/adapters/abstract/adapter.py
chainsync/adapters/base/__init__.py
chainsync/adapters/base/base.py
chainsync/adapters/decent/__init__.py
chainsync/adapters/decent/decent.py
chainsync/adapters/muse/__init__.py
chainsync/adapters/muse/muse.py
chainsync/adapters/peerplays/__init__.py
chainsync/adapters/peerplays/peerplays.py
chainsync/adapters/steem/__init__.py
chainsync/adapters/steem/steem.py
chainsync/adapters/steemv2/__init__.py
chainsync/adapters/steemv2/steem.py
chainsync/utils/__init__.py
chainsync/utils/http_client.py
chainsync-0.4.0.dist-info/DESCRIPTION.rst
chainsync-0.4.0.dist-info/METADATA
chainsync-0.4.0.dist-info/RECORD
chainsync-0.4.0.dist-info/WHEEL
chainsync-0.4.0.dist-info/metadata.json
chainsync-0.4.0.dist-info/top_level.txt
tests/__init__.py
tests/test_import.py
