Metadata-Version: 2.0
Name: chainsync
Version: 0.4.0
Summary: Utility to stream and sync blocks into other data sources
Home-page: http://github.com/aaroncox/chainsync
Author: Aaron Cox
Author-email: aaron@greymass.com
License: MIT
Platform: UNKNOWN
Provides-Extra: test
Requires-Dist: jsonrpcclient
Requires-Dist: requests
Provides-Extra: test
Requires-Dist: pep8; extra == 'test'
Requires-Dist: pytest; extra == 'test'
Requires-Dist: pytest-pylint; extra == 'test'
Requires-Dist: pytest-xdist; extra == 'test'
Requires-Dist: pytest-runner; extra == 'test'
Requires-Dist: pytest-pep8; extra == 'test'
Requires-Dist: pytest-cov; extra == 'test'
Requires-Dist: yapf; extra == 'test'
Requires-Dist: autopep8; extra == 'test'
